redis_ratelimit/__init__.py
redis_ratelimit/decorators.py
redis_ratelimit/exceptions.py
redis_ratelimit/utils.py
redis_ratelimit-1.0.3.dist-info/METADATA
redis_ratelimit-1.0.3.dist-info/RECORD
redis_ratelimit-1.0.3.dist-info/WHEEL
redis_ratelimit-1.0.3.dist-info/top_level.txt
