Metadata-Version: 2.1
Name: redis-ratelimit
Version: 1.0.3
Summary: A fixed window rate limiter based on Redis
Home-page: https://github.com/romantomjak/redis-ratelimit
Author: Roman Tomjak
Author-email: r.tomjaks@gmail.com
License: MIT
Keywords: redis rate-limit rate-limiter ratelimit ratelimiter
Platform: UNKNOWN
Classifier: Development Status :: 5 - Production/Stable
Classifier: Environment :: Web Environment
Classifier: Intended Audience :: Developers
Classifier: Intended Audience :: System Administrators
Classifier: License :: OSI Approved :: MIT License
Classifier: Operating System :: OS Independent
Classifier: Programming Language :: Python
Classifier: Programming Language :: Python :: 2
Classifier: Programming Language :: Python :: 3
Classifier: Programming Language :: Python :: Implementation :: CPython
Classifier: Topic :: Internet
Classifier: Topic :: Internet :: WWW/HTTP
Classifier: Topic :: Software Development :: Libraries :: Python Modules
Classifier: Topic :: Utilities
Requires-Dist: redis
